hexabyte_entropy/__init__.py
hexabyte_entropy/entropy.py
hexabyte_entropy/widgets/__init__.py
hexabyte_entropy/widgets/entropy_panel.py
hexabyte_entropy-0.1.4.dist-info/LICENSE
hexabyte_entropy-0.1.4.dist-info/METADATA
hexabyte_entropy-0.1.4.dist-info/WHEEL
hexabyte_entropy-0.1.4.dist-info/entry_points.txt
hexabyte_entropy-0.1.4.dist-info/RECORD
